deepod/__init__.py
deepod/version.py
deepod/core/__init__.py
deepod/core/base_model.py
deepod/core/base_networks.py
deepod/core/base_transformer_network.py
deepod/core/base_transformer_network_dev.py
deepod/core/network_utility.py
deepod/core/networks/__init__.py
deepod/core/networks/base_networks.py
deepod/core/networks/base_transformer_network_dev.py
deepod/core/networks/network_utility.py
deepod/core/networks/ts_network_dilated_conv.py
deepod/core/networks/ts_network_tcn.py
deepod/core/networks/ts_network_transformer.py
deepod/core/transformer/__init__.py
deepod/core/transformer/embed.py
deepod/core/transformer/selfattention_family.py
deepod/metrics/__init__.py
deepod/metrics/_anomaly_detection.py
deepod/metrics/_tsad_adjustment.py
deepod/model_selection/__init__.py
deepod/model_selection/fmms.py
deepod/model_selection/gene_feature.py
deepod/models/__init__.py
deepod/models/_local_test_.py
deepod/models/devnet.py
deepod/models/dif.py
deepod/models/dsad.py
deepod/models/dsvdd.py
deepod/models/feawad.py
deepod/models/goad.py
deepod/models/icl.py
deepod/models/neutral.py
deepod/models/prenet.py
deepod/models/rca.py
deepod/models/rdp.py
deepod/models/repen.py
deepod/models/rosas.py
deepod/models/slad.py
deepod/models/tabular/__init__.py
deepod/models/tabular/devnet.py
deepod/models/tabular/dif.py
deepod/models/tabular/dsad.py
deepod/models/tabular/dsvdd.py
deepod/models/tabular/feawad.py
deepod/models/tabular/goad.py
deepod/models/tabular/icl.py
deepod/models/tabular/neutral.py
deepod/models/tabular/prenet.py
deepod/models/tabular/rca.py
deepod/models/tabular/rdp.py
deepod/models/tabular/repen.py
deepod/models/tabular/rosas.py
deepod/models/tabular/slad.py
deepod/models/time_series/__init__.py
deepod/models/time_series/anomalytransformer.py
deepod/models/time_series/couta.py
deepod/models/time_series/devnet.py
deepod/models/time_series/dif.py
deepod/models/time_series/dsad.py
deepod/models/time_series/dsvdd.py
deepod/models/time_series/prenet.py
deepod-0.4.1.dist-info/LICENSE
deepod-0.4.1.dist-info/METADATA
deepod-0.4.1.dist-info/WHEEL
deepod-0.4.1.dist-info/top_level.txt
deepod-0.4.1.dist-info/RECORD
