Metadata-Version: 2.1
Name: deepod
Version: 0.4.1
Summary: UNKNOWN
Home-page: https://github.com/xuhongzuo/DeepOD
Author: Hongzuo Xu
Author-email: hongzuoxu@126.com
License: MIT License
Keywords: outlier detection,anomaly detection,deep anomaly detection,deep learning,data mining
Platform: UNKNOWN
Classifier: Programming Language :: Python :: 3.7
Classifier: Programming Language :: Python :: 3.8
Classifier: Programming Language :: Python :: 3.9
Classifier: Programming Language :: Python :: 3.10
Classifier: License :: OSI Approved :: BSD License
License-File: LICENSE
Requires-Dist: numpy (>=1.19)
Requires-Dist: scipy (>=1.5.1)
Requires-Dist: scikit-learn (>=0.20.0)
Requires-Dist: pandas (>=1.0.0)
Requires-Dist: torch (<1.13.1,>=1.10.0)
Requires-Dist: tqdm (>=4.62.3)
